JsonJiaochengWaiBowang/README.md
JsonJiaochengWaiBowang/__init__.py
JsonJiaochengWaiBowang/__main__.py
JsonJiaochengWaiBowang/file.epub
JsonJiaochengWaiBowang/index.html
JsonJiaochengWaiBowang/css/__init__.py
JsonJiaochengWaiBowang/css/annotations.css
JsonJiaochengWaiBowang/css/main.css
JsonJiaochengWaiBowang/css/normalize.css
JsonJiaochengWaiBowang/css/popup.css
JsonJiaochengWaiBowang/font/__init__.py
JsonJiaochengWaiBowang/font/fontello.eot
JsonJiaochengWaiBowang/font/fontello.svg
JsonJiaochengWaiBowang/font/fontello.ttf
JsonJiaochengWaiBowang/font/fontello.woff
JsonJiaochengWaiBowang/img/__init__.py
JsonJiaochengWaiBowang/img/annotator-glyph-sprite.png
JsonJiaochengWaiBowang/img/annotator-icon-sprite.png
JsonJiaochengWaiBowang/img/apple-touch-icon.png
JsonJiaochengWaiBowang/img/cancelfullscreen.png
JsonJiaochengWaiBowang/img/close.png
JsonJiaochengWaiBowang/img/fullscreen.png
JsonJiaochengWaiBowang/img/loader.gif
JsonJiaochengWaiBowang/img/menu-icon.png
JsonJiaochengWaiBowang/img/save.png
JsonJiaochengWaiBowang/img/saved.png
JsonJiaochengWaiBowang/img/settings-s.png
JsonJiaochengWaiBowang/img/settings.png
JsonJiaochengWaiBowang/img/star.png
JsonJiaochengWaiBowang/js/__init__.py
JsonJiaochengWaiBowang/js/epub.js
JsonJiaochengWaiBowang/js/epub.min.js
JsonJiaochengWaiBowang/js/epub.min.map
JsonJiaochengWaiBowang/js/hooks.min.js
JsonJiaochengWaiBowang/js/hooks.min.map
JsonJiaochengWaiBowang/js/reader.js
JsonJiaochengWaiBowang/js/reader.js.map
JsonJiaochengWaiBowang/js/reader.min.js
JsonJiaochengWaiBowang/js/reader.min.map
JsonJiaochengWaiBowang/js/hooks/__init__.py
JsonJiaochengWaiBowang/js/hooks/extensions/__init__.py
JsonJiaochengWaiBowang/js/hooks/extensions/highlight.js
JsonJiaochengWaiBowang/js/libs/__init__.py
JsonJiaochengWaiBowang/js/libs/jquery.min.js
JsonJiaochengWaiBowang/js/libs/localforage.min.js
JsonJiaochengWaiBowang/js/libs/screenfull.js
JsonJiaochengWaiBowang/js/libs/screenfull.min.js
JsonJiaochengWaiBowang/js/libs/zip.min.js
json_jiaocheng_wai_bowang-2024.3.3.0.dist-info/METADATA
json_jiaocheng_wai_bowang-2024.3.3.0.dist-info/WHEEL
json_jiaocheng_wai_bowang-2024.3.3.0.dist-info/entry_points.txt
json_jiaocheng_wai_bowang-2024.3.3.0.dist-info/top_level.txt
json_jiaocheng_wai_bowang-2024.3.3.0.dist-info/RECORD
